user_preferences_agent/VERSION
user_preferences_agent/__init__.py
user_preferences_agent/_currency.py
user_preferences_agent/_timezone.py
ac_py_template-0.2.0.dist-info/LICENSE
ac_py_template-0.2.0.dist-info/METADATA
ac_py_template-0.2.0.dist-info/WHEEL
ac_py_template-0.2.0.dist-info/RECORD
