Metadata-Version: 2.3
Name: ac-py-template
Version: 0.2.0
Summary: Simple agent summarize user preferences.
License: MIT
Author: Allen Chou
Author-email: f1470891079@gmail.com
Requires-Python: >=3.11,<4
Classifier: License :: OSI Approved :: MIT License
Classifier: Programming Language :: Python :: 3
Classifier: Programming Language :: Python :: 3.11
Classifier: Programming Language :: Python :: 3.12
Classifier: Programming Language :: Python :: 3.13
Requires-Dist: currency_codes
Requires-Dist: dictpress
Requires-Dist: google-language-support
Requires-Dist: openai
Requires-Dist: openai-agents
Requires-Dist: openai-usage (>=0.3.1,<1)
Requires-Dist: pydantic (>=2)
Requires-Dist: rich
Requires-Dist: rich-color-support
Requires-Dist: str-or-none
Requires-Dist: universal-message (>=0.3.0,<1)
Project-URL: Homepage, https://github.com/allen2c/user-preferences-agent
Project-URL: PyPI, https://pypi.org/project/user-preferences-agent/
Project-URL: Repository, https://github.com/allen2c/user-preferences-agent
